rakuten_do_dbt_processor/__init__.py
rakuten_do_dbt_processor/processor.py
rakuten_do_dbt_processor-0.1.0.dist-info/LICENSE
rakuten_do_dbt_processor-0.1.0.dist-info/METADATA
rakuten_do_dbt_processor-0.1.0.dist-info/WHEEL
rakuten_do_dbt_processor-0.1.0.dist-info/entry_points.txt
rakuten_do_dbt_processor-0.1.0.dist-info/top_level.txt
rakuten_do_dbt_processor-0.1.0.dist-info/RECORD
